ovos_PHAL_plugin_dotstar/__init__.py
ovos_PHAL_plugin_dotstar/animations.py
ovos_PHAL_plugin_dotstar/leds.py
ovos_PHAL_plugin_dotstar-0.0.1.dist-info/LICENSE
ovos_PHAL_plugin_dotstar-0.0.1.dist-info/METADATA
ovos_PHAL_plugin_dotstar-0.0.1.dist-info/WHEEL
ovos_PHAL_plugin_dotstar-0.0.1.dist-info/entry_points.txt
ovos_PHAL_plugin_dotstar-0.0.1.dist-info/top_level.txt
ovos_PHAL_plugin_dotstar-0.0.1.dist-info/zip-safe
ovos_PHAL_plugin_dotstar-0.0.1.dist-info/RECORD
